ai_content_audit/__init__.py
ai_content_audit/audit_manager.py
ai_content_audit/file_loader/__init__.py
ai_content_audit/file_loader/image_loader.py
ai_content_audit/loader/__init__.py
ai_content_audit/loader/checks_loader.py
ai_content_audit/loader/data_loader.py
ai_content_audit/models/__init__.py
ai_content_audit/models/audit_content_model.py
ai_content_audit/models/audit_decision_model.py
ai_content_audit/models/audit_options_item_model.py
ai_content_audit/models/audit_result_model.py
ai_content_audit/prompts/__init__.py
ai_content_audit/prompts/build_messages.py
ai_content_audit-0.3.0.dist-info/licenses/LICENSE
ai_content_audit-0.3.0.dist-info/METADATA
ai_content_audit-0.3.0.dist-info/WHEEL
ai_content_audit-0.3.0.dist-info/top_level.txt
ai_content_audit-0.3.0.dist-info/RECORD
