Metadata-Version: 2.4
Name: ai-content-audit
Version: 0.3.0
Summary: 基于大语言模型（LLM）的内容审核工具，支持文本与图像，自定义审核项配置，调用模型获得结构化判定结果，使用 OpenAI 兼容接口
Author-email: Apauto-to-all <apautotoall@outlook.com>
License-Expression: Apache-2.0
Project-URL: Homepage, https://github.com/Apauto-to-all/ai-content-audit
Requires-Python: >=3.12
License-File: LICENSE
Requires-Dist: openai>=1.109.1
Requires-Dist: pydantic>=2.11.9
Requires-Dist: structured-output-prompt>=1.0.0
Dynamic: license-file
